Metadata-Version: 1.0
Name: tim124-distributions
Version: 0.1
Summary: Gaussian and Binomial distributions
Home-page: UNKNOWN
Author: Tim Chan
Author-email: timchansdp@gmail.com
License: UNKNOWN
Platform: UNKNOWN
